locate/__init__.py
locate/locate.py
locate-1.1.0.dist-info/LICENSE
locate-1.1.0.dist-info/METADATA
locate-1.1.0.dist-info/WHEEL
locate-1.1.0.dist-info/top_level.txt
locate-1.1.0.dist-info/RECORD
