Metadata-Version: 2.1
Name: locate
Version: 1.1.0
Summary: Locate the file location of your current running script.
Home-page: https://github.com/heetbeet/locate
Author: Heetbeet
Author-email: sfstreicher@gmail.com
License: UNKNOWN
Platform: UNKNOWN
Classifier: Programming Language :: Python :: 3
Classifier: License :: Other/Proprietary License
Classifier: Operating System :: OS Independent
Requires-Python: >=3.4
License-File: LICENSE
